vectorium/__init__.py
vectorium/database.py
vectorium/utils.py
vectorium-0.1.0.dist-info/METADATA
vectorium-0.1.0.dist-info/WHEEL
vectorium-0.1.0.dist-info/top_level.txt
vectorium-0.1.0.dist-info/RECORD
