Metadata-Version: 2.1
Name: vectorium
Version: 0.1.0
Summary: Tools for storing embeddings in a database and querying them
Home-page: https://github.com/silvaan/vectorium
Author: Silvan Ferreira
Author-email: silvanfj@gmail.com
Classifier: Development Status :: 3 - Alpha
Classifier: Intended Audience :: Developers
Classifier: License :: OSI Approved :: MIT License
Classifier: Programming Language :: Python :: 3
Classifier: Programming Language :: Python :: 3.6
Classifier: Programming Language :: Python :: 3.7
Classifier: Programming Language :: Python :: 3.8
Classifier: Programming Language :: Python :: 3.9
Requires-Dist: numpy
Requires-Dist: torch
